regex_rs-0.2.4.dist-info/METADATA
regex_rs-0.2.4.dist-info/WHEEL
regex_rs-0.2.4.dist-info/license_files/LICENSE
regex_rs/__init__.py
regex_rs/__init__.pyi
regex_rs/py.typed
regex_rs/regex_rs.cp311-win32.pyd
regex_rs-0.2.4.dist-info/RECORD
