Metadata-Version: 2.1
Name: regex-rs
Version: 0.2.4
Classifier: Programming Language :: Rust
Classifier: Programming Language :: Python :: Implementation :: CPython
Classifier: Programming Language :: Python :: Implementation :: PyPy
License-File: LICENSE
Summary: Python bindings for the Rust regex crate.
Keywords: rust,maturin,regex
Requires-Python: >=3.7
Project-URL: repository, https://github.com/circuitsacul/regex-rs
